{
  "sorted_middleware": [],
  "middleware": {
    "/": {
      "files": [
        "server/edge/chunks/_bfc34f67._.js",
        "server/edge/chunks/[root-of-the-server]__8978dbac._.js",
        "server/edge/chunks/turbopack-edge-wrapper_63eff5ab.js"
      ],
      "name": "middleware",
      "page": "/",
      "matchers": [
        {
          "regexp": "/:nextData(_next/data/[^/]{1,})?/((?!_next|[^?]*\\.(?:html?|css|js(?!on)|jpe?g|webp|png|gif|svg|ttf|woff2?|ico|csv|docx?|xlsx?|zip|webmanifest)).*){(\\\\.json)}?",
          "originalSource": "/((?!_next|[^?]*\\.(?:html?|css|js(?!on)|jpe?g|webp|png|gif|svg|ttf|woff2?|ico|csv|docx?|xlsx?|zip|webmanifest)).*)"
        },
        {
          "regexp": "/:nextData(_next/data/[^/]{1,})?/(api|trpc)(.*){(\\\\.json)}?",
          "originalSource": "/(api|trpc)(.*)"
        }
      ],
      "wasm": [],
      "assets": [],
      "env": {
        "__NEXT_BUILD_ID": "development",
        "NEXT_SERVER_ACTIONS_ENCRYPTION_KEY": "uOq2eOAtNNBZ78bbM4c7iAAjNuun0p/fMPrq9qf2zFA=",
        "__NEXT_PREVIEW_MODE_ID": "14a817180f46857a582aa7dbfcf02736",
        "__NEXT_PREVIEW_MODE_ENCRYPTION_KEY": "d6114657ef198fb18f00b285725724bf5f7f3d4adbe2f45edde37050094d9059",
        "__NEXT_PREVIEW_MODE_SIGNING_KEY": "e22d41d41cdcd58120ce465fff8c0cd358c4e6b0889d899fc04bd36d5e15ede1"
      }
    }
  },
  "instrumentation": null,
  "functions": {}
}